neonrvm/__init__.py
neonrvm-0.2.0.dist-info/LICENSE
neonrvm-0.2.0.dist-info/WHEEL
neonrvm-0.2.0.dist-info/METADATA
neonrvm-0.2.0.dist-info/RECORD
