Metadata-Version: 2.1
Name: neonrvm
Version: 0.2.0
Summary: Python bindings for the neonrvm machine learning library.
Home-page: https://github.com/siavashserver/neonrvm
License: MIT
Keywords: Machine Learning Regression Relevance Vector Machine RVM Sparse Bayes
Author: Siavash Eliasi
Author-email: siavashserver@gmail.com
Requires-Python: >=3
Classifier: Development Status :: 4 - Beta
Classifier: Intended Audience :: Developers
Classifier: License :: OSI Approved :: MIT License
Classifier: Natural Language :: English
Classifier: Operating System :: OS Independent
Classifier: Programming Language :: Python
Classifier: Topic :: Scientific/Engineering
Classifier: Topic :: Software Development
Requires-Dist: numpy
